{"assets/audio/bgm1.wav":["assets/audio/bgm1.wav"],"assets/audio/bgm2.wav":["assets/audio/bgm2.wav"],"assets/audio/bgm3.wav":["assets/audio/bgm3.wav"],"assets/audio/bgm4.mp3":["assets/audio/bgm4.mp3"],"assets/audio/drop.wav":["assets/audio/drop.wav"],"assets/audio/game_over.wav":["assets/audio/game_over.wav"],"assets/audio/item_fast.mp3":["assets/audio/item_fast.mp3"],"assets/audio/item_heart.wav":["assets/audio/item_heart.wav"],"assets/audio/item_hide.mp3":["assets/audio/item_hide.mp3"],"assets/audio/item_keyboard.wav":["assets/audio/item_keyboard.wav"],"assets/audio/item_minus.wav":["assets/audio/item_minus.wav"],"assets/audio/item_mirror_create.mp3":["assets/audio/item_mirror_create.mp3"],"assets/audio/item_mirror_trigger.mp3":["assets/audio/item_mirror_trigger.mp3"],"assets/audio/item_plus.wav":["assets/audio/item_plus.wav"],"assets/audio/item_remove.wav":["assets/audio/item_remove.wav"],"assets/audio/item_shield_create.wav":["assets/audio/item_shield_create.wav"],"assets/audio/item_shield_trigger.wav":["assets/audio/item_shield_trigger.wav"],"assets/audio/item_slow.wav":["assets/audio/item_slow.wav"],"assets/audio/item_swap.wav":["assets/audio/item_swap.wav"],"assets/audio/remove.wav":["assets/audio/remove.wav"],"assets/audio/rotate.wav":["assets/audio/rotate.wav"],"assets/audio/winner.wav":["assets/audio/winner.wav"],"assets/images/fast.svg":["assets/images/fast.svg"],"assets/images/heart.svg":["assets/images/heart.svg"],"assets/images/hide.svg":["assets/images/hide.svg"],"assets/images/keyboard.svg":["assets/images/keyboard.svg"],"assets/images/minus.svg":["assets/images/minus.svg"],"assets/images/mirror.svg":["assets/images/mirror.svg"],"assets/images/multi.svg":["assets/images/multi.svg"],"assets/images/plus.svg":["assets/images/plus.svg"],"assets/images/remove.svg":["assets/images/remove.svg"],"assets/images/shield.svg":["assets/images/shield.svg"],"assets/images/single.svg":["assets/images/single.svg"],"assets/images/slow.svg":["assets/images/slow.svg"],"assets/images/start.svg":["assets/images/start.svg"],"assets/images/swap.svg":["assets/images/swap.svg"],"packages/cupertino_icons/assets/CupertinoIcons.ttf":["packages/cupertino_icons/assets/CupertinoIcons.ttf"]}